Metadata-Version: 2.1
Name: Spoonful
Version: 0.0.1
Summary: Basic Tools in Numerical Methods
Home-page: https://github.com/m3mc3/Spoonful.git
Author: Nikhil Murali
Author-email: nikhilmurali1301@gmail.com
License: MIT
Keywords: pypi,spoonful,scientific
Platform: UNKNOWN
Classifier: Development Status :: 3 - Alpha
Classifier: Intended Audience :: Science/Research
Classifier: Topic :: Scientific/Engineering :: Mathematics
Classifier: License :: OSI Approved :: MIT License
Classifier: Programming Language :: Python :: 3
Classifier: Programming Language :: Python :: 3.7
Classifier: Programming Language :: Python :: 3.8
Classifier: Programming Language :: Python :: 3.9
